BIpy/__init__.py
BIpy/data_processing.py
BIpy/session.py
BIpy/bci/__init__.py
BIpy/bci/classifier_process.py
BIpy/bci/inlets.py
BIpy/bci/models.py
BIpy/bci/stims.py
BIpy/bci/training_session.py
BIpy-1.dist-info/LICENSE
BIpy-1.dist-info/METADATA
BIpy-1.dist-info/WHEEL
BIpy-1.dist-info/top_level.txt
BIpy-1.dist-info/RECORD
