Metadata-Version: 2.1
Name: BIpy
Version: 1
Summary: py for BI
Home-page: UNKNOWN
Author: Adrien Schurger-Foy
License: BSD 3-Clause License
Platform: UNKNOWN
License-File: LICENSE
Requires-Dist: numpy (==1.20.3)
Requires-Dist: pylsl (==1.13.6)
Requires-Dist: psychopy (==2021.2.0)
Requires-Dist: mne (==0.23.0)
Requires-Dist: pyxdf (==1.16.3)
Requires-Dist: scikit-learn (==0.24.2)
